trgenpy/__init__.py
trgenpy/connection.py
trgenpy/crc.py
trgenpy/implementation.py
trgenpy/instruction.py
trgenpy/trgen.py
trgenpy/trgen_pin.py
trgenpy/test/__init__.py
trgenpy/test/test_connection.py
trgenpy/test/test_crc.py
trgenpy/test/test_implementation.py
trgenpy/test/test_instruction.py
trgenpy/test/test_trgen.py
trgenpy/test/test_trgen_pin.py
trgenpy-1.0.0.dist-info/licenses/LICENSE
trgenpy-1.0.0.dist-info/METADATA
trgenpy-1.0.0.dist-info/WHEEL
trgenpy-1.0.0.dist-info/top_level.txt
trgenpy-1.0.0.dist-info/RECORD
