Metadata-Version: 2.4
Name: trgenpy
Version: 1.0.0
Summary: ## A Python library for Trgen Device
Home-page: https://gitlab.com/b00leant/trgenpy
Author: Stefano Latini
Author-email: Stefano Latini <stefanoelatini@hotmail.it>
License: MIT License
Project-URL: Homepage, https://gitlab.com/b00leant/trgenpy
Project-URL: Repository, https://gitlab.com/b00leant/trgenpy
Classifier: Programming Language :: Python :: 3.7
Classifier: Programming Language :: Python :: 3.8
Classifier: Programming Language :: Python :: 3.9
Classifier: Programming Language :: Python :: 3
Classifier: License :: OSI Approved :: MIT License
Classifier: Operating System :: OS Independent
Requires-Python: >=3.10
License-File: LICENSE
Dynamic: author
Dynamic: home-page
Dynamic: license-file
Dynamic: requires-python
